carte/__init__.py
carte/_vendor/__init__.py
carte/_vendor/boltons/__init__.py
carte/_vendor/boltons/setutils.py
carte/carte.py
carte/config.py
carte/exceptions.py
carte/resources/__init__.py
carte/resources/countries.py
carte/resources/geonames.py
carte/resources/postal_codes.py
carte/resources/resource.py
carte/utils.py
carte-0.2.2.dist-info/LICENSE
carte-0.2.2.dist-info/WHEEL
carte-0.2.2.dist-info/METADATA
carte-0.2.2.dist-info/RECORD
