Metadata-Version: 2.1
Name: carte
Version: 0.2.2
Summary: Carte is a flexible, extensible reverse-geocode library.
License: LGPL-2.1-or-later
Author: Payson Wallach
Author-email: payson@fourpeaksstudios.com
Requires-Python: >=3.7,<4.0
Classifier: License :: OSI Approved
Classifier: Programming Language :: Python :: 3
Classifier: Programming Language :: Python :: 3.7
Classifier: Programming Language :: Python :: 3.8
Requires-Dist: appdirs (>=1.4.3,<2.0.0)
Requires-Dist: initable (>=0.2.0,<0.3.0)
Requires-Dist: scipy (>=1.4.1,<2.0.0)
